{"Category":"Componentes","SubCategory":"Chasis","Images":["/images/products/chasis-msi-mag-forge-321r-airflow-1.webp","/images/products/chasis-msi-mag-forge-321r-airflow-2.webp","/images/products/chasis-msi-mag-forge-321r-airflow-3.webp","/images/products/chasis-msi-mag-forge-321r-airflow-4.webp","/images/products/chasis-msi-mag-forge-321r-airflow-5.webp"],"Description":"Model\nBrand: MSI\nModel: MAG FORGE 321R AIRFLOW\n\n\nDetails\nType: ATX Mid Tower\nColor: Black\nCase Material: ABS Plastic / SPCC Steel / Tempered Glass\nMotherboard Compatibility: Micro ATX / ITX / Mini ITX\nLED: ARGB\n\n\nExpansion\nInternal 3.5\" Drive Bays: 2x3.5\", Compatible with 2.5\", Max up to 3x2.5\"\nInternal 2.5\" Drive Bays: 1\nExpansion Slots: 7\n\n\nFront Panel Ports\nFront Ports: 1 x USB 3.2 Gen 2x2 Type-C, 2 x USB 3.2 Gen 1 Type-A, 1 x Audio\n\n\nCooling System\nFan Options: Top: 3x 120mm or 2 x140mm\nFront: 3x 120mm or 2 x140mm\nRear: 1x 120mm\nSide: 2 x 120 mm\nPSU Shroud: 2 x 120 mm\n\nFan Included:\nFront: 3x 120mm A-RGB Fan\nRear: 1x 120mm A-RGB Fan\nRadiator Options: Top: 120/140/240/280/360mm \nFront: 120/140/240mm \nRear : 120mm\n\n\nDimensions & Weight\nMax GPU Length: 390 mm\nMax CPU Cooler Height: 160 mm\nMax PSU Length: 200 mm\nDimensions (H x W x D): 18.60 x 8.26 x 19.60 inches\nWeight: 15.54 lbs","Price":189.00,"Features":["Tempered Glass","Mesh","HUB ARGB-FAN x4","4xFan ARGB","2xUSB3","USB-C","360mm Top","160mm CPU","390mm GPU","200mm* PSU","240mm Front","2xHDD","ATX","Gamer","Mid Tower","Negro","Case"],"Date":"2025-02-16T14:05:47.728585-05:00","Update":"2025-02-16T20:59:31.9673319-05:00","Label":"Chasis MSI MAG Forge 321R AirFlow"}