{"Category":"Componentes","SubCategory":"Disipador Líquido","Images":["/images/products/corsair-hydro-xc7-rgb-cpu-water-block-1.webp","/images/products/corsair-hydro-xc7-rgb-cpu-water-block-2.webp","/images/products/corsair-hydro-xc7-rgb-cpu-water-block-3.webp","/images/products/corsair-hydro-xc7-rgb-cpu-water-block-4.webp","/images/products/corsair-hydro-xc7-rgb-cpu-water-block-5.webp","/images/products/corsair-hydro-xc7-rgb-cpu-water-block-6.webp"],"Description":"Hydro X Series XC7 RGB CPU Water Block (115X/AM4)\nThe CORSAIR Hydro X Series XC7 RGB CPU Water Block combines premium construction, vivid RGB lighting, and extreme cooling performance to become the centerpiece of your water cooling loop.\n\n\nUNCOMPROMISING CPU COOLING\nThe XC7’s nickel-plated copper cold plate and more than 60 high-efficiency micro-cooling fins efficiently draw heat away from your CPU, lowering operating temperatures and allowing for maximum overclocks.\n\nVIVID INTEGRATED RGB LIGHTING\n16 Individually addressable RGB LEDs deliver 360° of stunning customizable RGB lighting when combined with a CORSAIR iCUE RGB lighting controller.*\n\n\nSEE YOUR COOLING\nA transparent flow chamber shows off your coolant and enhances RGB effects.\n\nIntelligent Control. Unlimited Possibilities.\nCombine with a CORSAIR iCUE RGB lighting controller* and powerful CORSAIR iCUE software to allow you to customize and instantly sync RGB lighting across all your CORSAIR RGB products including water blocks, fans, keyboard, LED light strips and more.","Price":49.00,"Features":["LGA 1200","AM4","Black"],"Date":"2025-09-24T02:35:02.6492911-04:00","Update":"2025-09-24T02:48:19.7140394-04:00","Label":"Corsair Hydro XC7 RGB CPU Water Block"}