{"Category":"Componentes","SubCategory":"Disipador por Aire","Images":["/images/products/disipador-be-quiet-pure-rock-pro-3-1.webp","/images/products/disipador-be-quiet-pure-rock-pro-3-2.webp","/images/products/disipador-be-quiet-pure-rock-pro-3-3.webp","/images/products/disipador-be-quiet-pure-rock-pro-3-4.webp","/images/products/disipador-be-quiet-pure-rock-pro-3-5.webp","/images/products/disipador-be-quiet-pure-rock-pro-3-6.webp"],"Description":"Model\nBrand: be quiet!\nModel: Pure Rock Pro 3\nPart Number: BK041\n\n\nDetails\nColor: Silver\nType: CPU Air Cooler\nFan Size: 120mm\nCPU Socket Compatibility: AMD Socket AM4 / AMD Socket AM5 / Intel LGA 1150 / Intel LGA 1151 / Intel LGA 1155 / Intel LGA 1200 / Intel LGA 1700 / Intel LGA 1851\nBearing Type: Rifle\nTDP: 250W\nRPM: 2000 RPM max\nAir Flow: 59.6 CFM / 101.2 m3/h max\nNoise Level: 34.8 dBA max\nPower Connector: 4-pin PWM\nPressure: 2.41mmH2O\nLED: Non LED\nHeatsink Material: Aluminum\nFan Mounting Types to Heatsink: Vertical\n\n\nDimensions & Weight\nMax CPU Cooler Height: 155 mm\nHeatsink Dimensions: 155 x 124 x 114mm\nWeight: 1124g","Price":105.00,"Features":["2000rpm","250W","Dual Tower","6xPipes","2xFan","120mm","59.6cfm","34.8dba"],"Date":"2025-06-16T22:45:22.0390994-04:00","Update":"2025-06-17T16:55:02.2795852-04:00","Label":"Disipador Be Quiet Pure Rock Pro 3"}