{"Category":"Componentes","SubCategory":"Fuente","Images":["/images/products/fuente-thermaltake-tr2-tr-500-500w-1.webp","/images/products/fuente-thermaltake-tr2-tr-500-500w-2.webp","/images/products/fuente-thermaltake-tr2-tr-500-500w-3.webp","/images/products/fuente-thermaltake-tr2-tr-500-500w-4.webp"],"Description":"TR-500P\nModelo TR2-500AH2NFB\nTipo Intel ATX 12V 2.3\nMax. Capacidad de salida 500W\nColor Negro\nDimensión 150 mm x 86 mm x 140 mm\nPFC activo\nBuena señal de potencia 100-500 mseg\nTiempo de espera 17 mseg (mínimo) a plena carga a 115Vac / 230Vac de entrada.\nCorriente de entrada 7A - 3.5A\nRango de frecuencia de entrada 50 Hz - 60 Hz\nVoltaje de entrada 100 Vac- 240 Vac\ntemperatura de operacion + 10  a + 50 \nHumedad de funcionamiento 5% a 95%, sin condensación\nTemperatura de almacenamiento -20  a +80 \nHumedad de almacenamiento 5% a 95%, sin condensación\nSistema de refrigeración Ventilador de 120mm: 2200 RPM ± 10%\nEficiencia 82-85% de eficiencia a 20-100% de carga\nMTBF Mínimo 100.000 horas\nAprobación de seguridad UL / CUL, FCC, TUV, VDE, CE, CB, BSMI, GOST","Price":75.00,"Features":["6x SATA","35A","1x 6+2-Pin","1x 4+4 EPS","140mm","PSU","ATX"],"Date":"2025-04-24T14:41:47.2516634-04:00","Update":"2025-04-24T14:43:46.5109523-04:00","Label":"Fuente Thermaltake TR2 TR-500 500W"}