{"Category":"Componentes","SubCategory":"Fuente","Images":["/images/products/fuente-msi-mag-a850gl-850w-1.webp","/images/products/fuente-msi-mag-a850gl-850w-2.webp","/images/products/fuente-msi-mag-a850gl-850w-3.webp","/images/products/fuente-msi-mag-a850gl-850w-4.webp","/images/products/fuente-msi-mag-a850gl-850w-5.webp"],"Description":"General\nBrand: MSI\nModel: MAG A850GL PCIE5\n\n\nDetails\nColor: Black\nType: ATX12V\nMaximum Power: 850 W\nFans: 1 x 120 mm\nPFC: Active\n+12V Rails: Single\nSATA Power Connector: 8\nMax PSU Length: 150 mm\nModular: Full Modular\nEnergy-Efficient: 80 PLUS GOLD Certified\nProtection: OVP,  OCP, OTP, OPP , SCP, UVP\nInput Voltage: 100 - 240 V\nInput Frequency Range: 47 - 63 Hz\nInput Current: 12A\nOutput: +3.3V@20A, +5V@20A, +12V@70.5A, -12V@0.3A, +5VSB@2.5A\nConnectors: 1 x MB (24/20 pins)\n2 x CPU (8/4 pins)\n4 x PCIe (8/6 pins)\n1 x 12VHPWR (PCI-E 5.0)\n8 x SATA\n4 x Molex\n1 x Molex to FDD Adapter\n\n\nDimension & Weight\nDimensions: 11.81 * 8.66 * 4.92\"","Price":185.00,"Features":["ATX 3.0","70A","80+ Gold","Full Modular","1x 16Pin","4x 6+2Pin","8x SATA","2x 4+4 EPS","4x Molex","140mm","PSU","ATX"],"Date":"2024-04-11T02:49:01.5018153-04:00","Update":"2025-01-19T23:48:18.1762495-05:00","Label":"Fuente MSI MAG A850GL 850W"}