{"Category":"Periféricos","SubCategory":"HUB USB","Images":["/images/products/hub-ludtbf-usb-c-4xusb-1.webp","/images/products/hub-ludtbf-usb-c-4xusb-2.webp","/images/products/hub-ludtbf-usb-c-4xusb-3.webp","/images/products/hub-ludtbf-usb-c-4xusb-4.webp","/images/products/hub-ludtbf-usb-c-4xusb-5.webp","/images/products/hub-ludtbf-usb-c-4xusb-6.webp"],"Description":"Puertos duales USB-C y USB-A: Este concentrador cuenta con puertos USB-A y USB-C, lo que reduce los costos de equipo\nHub USB multifuncional 4 en 1: este concentrador USB-C expande fácilmente sus dispositivos con 4 puertos USB adicionales, 1 USB 3.0 y 3 puertos USB 2.0\n\nTransferencia de datos de alta velocidad: admite velocidades de transferencia de datos de hasta 5 Gbps (USB 3.0), 480 Mbps (USB 2.0) y 12 Mbps (USB 1.1)\n\nAmplia gama de dispositivos: compatible con MacBook Pro, MacBook Air, iMac, PS4 Pro, Surface Pro, computadoras portátiles y más\nPlug and Play: no se necesitan controladores ni software\nDiseño duradero: fabricado con material de fibra fuerte y flexible que aumenta la resistencia a la tracción en un 200%, capaz de soportar más de 20,000 curvas. La carcasa de aluminio premium garantiza una excelente disipación del calor\n\nEste concentrador USB puede expandir fácilmente uno de los puertos USB de su computadora en cuatro puertos (soporte de carga).\nAdmite 4 puertos para trabajar al mismo tiempo, sin ninguna presión, y mantener la temperatura en el rango medio.\nPlug and play, sin necesidad de controlador, fácil de usar","Price":11.00,"Features":["1x USB 3.0","3x USB 2.0","Aluminio","Premium","USB-A"],"Date":"2025-01-19T23:48:51.0619805-05:00","Update":"2025-01-20T10:42:26.0863679-05:00","Label":"HUB LUDTBF USB-C 4xUSB"}