{
  "Category": "Componentes",
  "SubCategory": "Tarjeta Gráfica",
  "Images": [
    "/images/products/msi-mech-radeon-rx-6650-xt-1.webp",
    "/images/products/msi-mech-radeon-rx-6650-xt-2.webp",
    "/images/products/msi-mech-radeon-rx-6650-xt-3.webp",
    "/images/products/msi-mech-radeon-rx-6650-xt-4.webp",
    "/images/products/msi-mech-radeon-rx-6650-xt-5.webp",
    "/images/products/msi-mech-radeon-rx-6650-xt-6.webp",
    "/images/products/msi-mech-radeon-rx-6650-xt-7.webp"
  ],
  "Description": "Model\nBrand: MSI\nSeries: Mech\nModel: RX 6650 XT MECH 2X 8G OC\n\n\nInterface\nInterface: PCI Express 4.0\n\n\nChipset\nChipset Manufacturer: AMD\nGPU Series: AMD Radeon RX 6000 Series\nGPU: Radeon RX 6650 XT\nArchitechture: RDNA 2\nStream Processors: 2048 Stream Processors\n\n\nMemory\nEffective Memory Clock: 17.5 Gbps\nMemory Size: 8GB\nMemory Interface: 128-Bit\nMemory Type: GDDR6\n\n\n3D API\nDirectX: DirectX 12 Ultimate\nOpenGL: OpenGL 4.6\n\n\nPorts\nMulti-Monitor Support: 4\nHDMI: 1 x HDMI 2.1\nDisplayPort: 3 x DisplayPort 1.4a\n\n\nDetails\nMax Resolution: 7680 x 4320\nCooler: Double Fans\nThermal Design Power: 175W\nPower Connector: 8-Pin\nHDCP Ready: Yes\n\n\nForm Factor & Dimensions\nMax GPU Length: 235 mm\nCard Dimensions (L x H): 9.25\" x 4.92\"",
  "Price": 319.00,
  "Features": [
    "8GB",
    "2xFan",
    "1x8Pin",
    "550WR",
    "235mm",
    "Radeon",
    "AMD",
    "GPU"
  ],
  "Date": "2023-07-17T23:39:40.6107252-04:00",
  "Update": "2023-08-16T11:17:10.2327626-04:00",
  "Discount": 0.0,
  "Label": "MSI Mech Radeon RX 6650 XT"
}