{"Category":"Componentes","SubCategory":"Memoria RAM","Images":["/images/products/ram-ddr4-corsair-vengeance-rgb-pro-sl-16gb-3600mhz-7ch2g-1.webp","/images/products/ram-ddr4-corsair-vengeance-rgb-pro-sl-16gb-3600mhz-7ch2g-2.webp","/images/products/ram-ddr4-corsair-vengeance-rgb-pro-sl-16gb-3600mhz-7ch2g-3.webp","/images/products/ram-ddr4-corsair-vengeance-rgb-pro-sl-16gb-3600mhz-7ch2g-4.webp"],"Description":"Model\nBrand: CORSAIR\nSeries: Vengeance RGB Pro SL\nModel: CMH16GX4M2D3600C18\n\n\nDetails\nCapacity: 16GB (2 x 8GB)\nType: 288-Pin PC RAM\nSpeed: DDR4 3600 (PC4 28800)\nCAS Latency: CL18\nTiming: 18-22-22-42\nVoltage: 1.35V\nBIOS/Performance Profile: Intel XMP 2.0\nColor: Black\nHeat Spreader: Anodized Aluminum\nFeatures: Illuminate your system with vivid, animated lighting from ten individually addressable, ultra-bright RGB LEDs per module.\n\nChoose from dozens of preset lighting profiles, or create your own in CORSAIR iCUE software.\n\nJust 44mm tall for wide compatibility with air coolers such as the CORSAIR A500.\n\nOptimized for maximum bandwidth and tight response times on the latest Intel and AMD DDR4 motherboards.\n\nA custom performance PCB provides the highest signal quality for the greatest level of performance and stability.\n\nVENGEANCE RGB PRO SL modules use only tightly screened memory chips, for extended overclocking potential.\n\nTake control with CORSAIR iCUE software and synchronize lighting with other CORSAIR RGB products, including coolers, keyboards and fans.\n\nA solid aluminum heat-spreader improves thermal conductivity for superb memory cooling even when overclocked, with modern styling to complement your RGB lighting.\n\nSupports Intel XMP 2.0 for simple one-setting installation and setup.\nRecommend Use: AMD &amp; Intel Compatible / AMD 300 Series / AMD 400 Series / AMD 500 Series / AMD Ryzen Compatible / AMD X570 / Intel 300 Series / Intel 400 Series / Intel 500 Series / Intel 600 Series\nLED Color: RGB","Price":73.00,"Features":["2x8GB","CL18","Dual Channel","Disipadas"],"Date":"2025-04-24T14:41:48.2913907-04:00","Update":"2025-04-24T14:43:56.2069887-04:00","Def":true,"Label":"RAM DDR4 Corsair Vengeance RGB Pro SL 16GB 3600mhz Black"}