{"Category":"Componentes","SubCategory":"Disco Sólido","Images":["/images/products/ssd-m2-intel-660p-2tb-1.webp","/images/products/ssd-m2-intel-660p-2tb-2.webp","/images/products/ssd-m2-intel-660p-2tb-3.webp"],"Description":"Capacidad de almacenamiento 2B\nM2. Factor de forma 2280\nInterfaz PCIe NVMe 3.0 x4\nVelocidades de lectura secuencial de 1800 MB/s. 1800 velocidades de escritura secuencial. Intel QLC 3D NAND\n\nEl SSD interno NVMe M.2 de 2 TB 660P de Intel cuenta con tecnología QLC (Quad Level Cell), que ofrece más capacidad por celda NAND, lo que permite un almacenamiento de estado sólido a precios más asequibles. Además, utiliza la interfaz PCIe NVMe 3.0 x4 que tiene un mayor ancho de banda en comparación con SATA para velocidades de lectura y escritura secuenciales de hasta 1800 MB/s y 1800 MB/s, respectivamente. Con un factor de forma M.2 2280, el Intel 660P SSD es compatible con una amplia variedad de portátiles, computadoras de escritorio y dispositivos móviles.","Price":245.00,"Features":["1800mbr","1800mbw","400TBW","UltraM2"],"Date":"2026-07-13T21:41:50.723255-04:00","Update":"2026-07-13T21:52:25.3779152-04:00","Label":"SSD M.2 Intel 660P 2TB"}