{
  "Category": "Componentes",
  "SubCategory": "Tarjeta Gráfica",
  "Images": [
    "/images/products/tarjeta-de-video-gigabyte-rtx-4070-gaming-oc-v2-12-d4jz6k-1.webp",
    "/images/products/tarjeta-de-video-gigabyte-rtx-4070-gaming-oc-v2-12-d4jz6k-2.webp",
    "/images/products/tarjeta-de-video-gigabyte-rtx-4070-gaming-oc-v2-12-d4jz6k-3.webp",
    "/images/products/tarjeta-de-video-gigabyte-rtx-4070-gaming-oc-v2-12-d4jz6k-4.webp",
    "/images/products/tarjeta-de-video-gigabyte-rtx-4070-gaming-oc-v2-12-d4jz6k-5.webp",
    "/images/products/tarjeta-de-video-gigabyte-rtx-4070-gaming-oc-v2-12-d4jz6k-6.webp"
  ],
  "Description": "Model\nBrand: GIGABYTE\nSeries: Gaming\nModel: GV-N4070GAMING OCV2-12GD\n\n\nInterface\nInterface: PCI Express 4.0 x16\n\n\nChipset\nChipset Manufacturer: NVIDIA\nGPU Series: NVIDIA GeForce RTX 40 Series\nGPU: GeForce RTX 4070\n\n\nMemory\nEffective Memory Clock: 21000 MHz (21 Gbps)\nMemory Size: 12GB\nMemory Interface: 192-Bit\nMemory Type: GDDR6X\n\n\n3D API\nDirectX: DirectX 12\nOpenGL: OpenGL 4.6\n\n\nPorts\nMulti-Monitor Support: 4\nHDMI: 1 x HDMI\nDisplayPort: 3 x DisplayPort\n\n\nDetails\nMax Resolution: 7680 x 4320\nCooler: Triple Fans\nThermal Design Power: 150W\nRecommended PSU Wattage: 650W\nPower Connector: 8-Pin\n\n\nForm Factor & Dimensions\nForm Factor: ATX\nMax GPU Length: 300 mm\nSlot Width: 2.5 Slots",
  "Price": 660.00,
  "Features": [
    "DLSS3",
    "3xfan",
    "1x8Pin",
    "650WR",
    "300mm",
    "GeForce",
    "NVIDIA",
    "GPU",
    "Gráfica"
  ],
  "Date": "2024-04-11T02:49:46.3017721-04:00",
  "Update": "2024-05-04T08:26:33.9935371-04:00",
  "Label": "Tarjeta de Video Gigabyte RTX 4070 Gaming OC V2 12GB"
}