{"Category":"Periféricos","SubCategory":"Teclado","Images":["/images/products/teclado-logitech-g413-se-1.webp","/images/products/teclado-logitech-g413-se-2.webp","/images/products/teclado-logitech-g413-se-3.webp"],"Description":"Model\nBrand: Logitech\nName: G413 SE\nModel: 920-010433\n\n\nKeyboard\nMechanical Keyboard: Yes\nKey Switch Type: Tactile\nKeyboard Color: Black","Price":89.00,"Features":["Mecánico","Gaming","Full","TKL"],"Date":"2024-02-20T04:08:15.7576333-05:00","Update":"2024-02-20T07:14:58.417012-05:00","Label":"Teclado Logitech G413 SE"}