{"Category":"Periféricos","SubCategory":"Teclado","Images":["/images/products/teclado-corsair-k70-lux-rgb-cherry-brown-1.webp","/images/products/teclado-corsair-k70-lux-rgb-cherry-brown-2.webp","/images/products/teclado-corsair-k70-lux-rgb-cherry-brown-3.webp","/images/products/teclado-corsair-k70-lux-rgb-cherry-brown-4.webp"],"Description":"Model\nBrand: Corsair\nName: K70 LUX\nModel: CH-9101013-NA\n\n\nKeyboard\nKeyboard Interface: USB\nDesign Style: Gaming\nPalm Rest: Detachable\nMechanical Keyboard: Yes\nKey Switch Type: Cherry MX RGB Silent\nKeyboard Color: Black\nDimensions: 1.53\" x 17.20\" x 6.60\"\nBacklit: Yes\nType: Wired\n\n\nMouse\nMouse Included: No\n\n\nFeatures\nFeatures: Aircraft-grade Anodized Brushed Aluminum Frame: The lightweight and rugged durability you need for a keyboard that’s going to see a lot of action\n\n100% CHERRY MX Silent Keyswitches: Patented noise reduction technology makes key presses up to 30% quieter than other mechanical gaming keyboards\n\nMulticolor Per-Key Dynamic Backlighting For Unlimited Game Customization: Pick a unique color and illumination level for each key for sophisticated keymaps and dramatic animations and effects\n\nThe Power of CUE: CORSAIR Utility Engine (CUE) software enables sophisticated macro programming and fast, fluid dynamic multicolor illumination for an enlightened gaming experience\n\nUSB Pass-Through Port: Positioned for uninterrupted game play and ready for your mouse or wireless headset adapter\n\n100% Anti-Ghosting With Full Key Rollover On USB: Reliably accurate performance, no matter how fast you are\n\nFPS and MOBA keycap sets: Textured and contoured keycaps provide maximum grip and enhanced feel\n\n\nPackage Contents\nPackage Contents: Corsair Gaming K70 LUX RGB MX SILENT Mechanical Keyboard, Warranty Card, Quick Start Guide, FPS and MOBA keycap sets","Price":135.00,"Features":["Mecánico","RGB","Palm-Rest","Retroiluminado","Anti-Ghosting","Gaming","Full"],"Date":"2024-06-07T05:57:53.4587984-04:00","Update":"2024-06-07T07:32:47.8509436-04:00","Label":"Teclado Corsair K70 LUX RGB Cherry Brown"}